opaquepy-0.6.0.dist-info/METADATA
opaquepy-0.6.0.dist-info/WHEEL
opaquepy/lib.py
opaquepy/__init__.py
opaquepy/py.typed
opaquepy/opaquepy.cpython-311-x86_64-linux-gnu.so
opaquepy-0.6.0.dist-info/RECORD
