Metadata-Version: 2.4
Name: opaquepy
Version: 0.6.0
Summary: Python bindings for opaque-ke.
Author: Tip ten Brink
Author-email: 75669206+tiptenbrink@users.noreply.github.com
License: Apache-2.0
Requires-Python: >=3.9, <3.14
